<?xml version="1.0" encoding="UTF-8"?>
<database>
    <element attributes="update_synch=true" extends="sys_metadata" label="LUDI Voice" max_length="40" name="x_snc_ludi_v1_ludi_voice" type="collection">
        <element label="Active" max_length="40" name="active" type="boolean"/>
        <element default="/*&#13;&#10;annyang.addCommands({&#13;&#10;        //in the voice command, use () around words that are not nessairly required. &#13;&#10;        //use *tag for a command that could be any word. when you need to use it in the rest of the command, use tag like a variable.&#13;&#10;&#9;'&lt;insert voice command&gt;': function() {&#13;&#10;                 //getRandomResponse sends a random response acknowledging the command&#13;&#10;                 getRandomResponse();&#13;&#10;                //any server script needs to be done with GlideAjax&#13;&#10;                //client script works fine&#13;&#10;&#9;&#9;var ga2 = new GlideAjax(&lt;Ajax script include&gt;);&#13;&#10;&#9;&#9;ga2.addParam('sysparm_name', '&lt;sysparm_name&gt;');&#13;&#10;&#9;&#9;ga2.getXMLAnswer(function(answer) {&#13;&#10;&#9;&#9;&#9;responsiveVoice.speak('&lt;type what you want LUDI to say&gt;', &quot;UK English Male&quot;, {&#13;&#10;&#9;&#9;&#9;&#9;volume: 1&#13;&#10;&#9;&#9;&#9;&#9;&#13;&#10;&#9;&#9;&#9;});&#9;&#13;&#10;&#9;&#9;&#9;parent.window.location = &quot;&lt;link if there is a redirect&gt;&quot;&#13;&#10;&#9;&#9;});&#13;&#10;&#9;&#9;&#13;&#10;&#9;&#9;&#13;&#10;&#9;&#9;&#13;&#10;&#9;&#9;&#13;&#10;&#9;&#9;SpeechKITT.abortRecognition();&#13;&#10;&#9;}&#13;&#10;&#9;&#13;&#10;});&#13;&#10;*/" label="Command" max_length="8000" name="command" type="script"/>
        <element label="Input" max_length="200" name="input" type="string"/>
        <element label="Needs Command" max_length="40" name="needs_command" type="boolean"/>
        <element choice="1" label="Type" max_length="40" name="type" type="choice">
            <choice>
                <element label="Voice Response" sequence="100" value="voice_response"/>
                <element label="Run Script" sequence="200" value="run_script"/>
            </choice>
        </element>
    </element>
</database>
